inopaicli/__init__.py
inopaicli/manage.py
inopaicli/commands/actions_download_all.py
inopaicli/commands/actions_update.py
inopaicli/commands/app_get.py
inopaicli/commands/app_get_element_definitions.py
inopaicli/commands/app_get_schema.py
inopaicli/commands/app_get_workflow_states.py
inopaicli/commands/app_update.py
inopaicli/commands/commands_print.py
inopaicli/commands/curl_print.py
inopaicli/commands/download_files.py
inopaicli/commands/entries_export.py
inopaicli/commands/entries_export_excel.py
inopaicli/commands/entries_sync.py
inopaicli/commands/entries_update.py
inopaicli/commands/exports_download_all.py
inopaicli/commands/exports_update.py
inopaicli/commands/flatt_app_schema_and_export_entries.py
inopaicli/commands/group_get.py
inopaicli/commands/update_app_instance.py
inopaicli/concepts/app/api.py
inopaicli/concepts/app_action/api.py
inopaicli/concepts/app_action/functions.py
inopaicli/concepts/app_export/api.py
inopaicli/concepts/app_view/api.py
inopaicli/concepts/app_view/functions.py
inopaicli/concepts/download_files/__init__.py
inopaicli/concepts/download_files/api.py
inopaicli/concepts/download_files/functions.py
inopaicli/concepts/group/api.py
inopaicli/concepts/group/functions.py
inopaicli/concepts/io/api.py
inopaicli/concepts/io/constants.py
inopaicli/concepts/io/functions.py
inopaicli/concepts/io_search/api.py
inopaicli/concepts/io_search/constants.py
inopaicli/concepts/io_search/excel_export.py
inopaicli/concepts/io_search/functions.py
inopaicli/core/api.py
inopaicli/core/arguments.py
inopaicli/core/auth.py
inopaicli/core/commands.py
inopaicli/core/config.py
inopaicli/core/constants.py
inopaicli/core/export.py
inopaicli/core/file.py
inopaicli/core/util.py
inopaicli-1.1.1.dist-info/LICENSE
inopaicli-1.1.1.dist-info/METADATA
inopaicli-1.1.1.dist-info/WHEEL
inopaicli-1.1.1.dist-info/entry_points.txt
inopaicli-1.1.1.dist-info/top_level.txt
inopaicli-1.1.1.dist-info/RECORD
